st_triggers/__init__.py
st_triggers/example.py
st_triggers/frontend/build/asset-manifest.json
st_triggers/frontend/build/bootstrap.min.css
st_triggers/frontend/build/index.html
st_triggers/frontend/build/static/js/main.7327f606.js
st_triggers/frontend/build/static/js/main.7327f606.js.LICENSE.txt
st_triggers/frontend/build/static/js/main.7327f606.js.map
st_triggers-0.0.1.dist-info/LICENSE
st_triggers-0.0.1.dist-info/METADATA
st_triggers-0.0.1.dist-info/WHEEL
st_triggers-0.0.1.dist-info/top_level.txt
st_triggers-0.0.1.dist-info/RECORD
